roq/__init__.py
roq/client.py
roq/roq.py
roq/router.py
roq-0.0.2.dist-info/LICENSE.txt
roq-0.0.2.dist-info/METADATA
roq-0.0.2.dist-info/WHEEL
roq-0.0.2.dist-info/top_level.txt
roq-0.0.2.dist-info/RECORD
