Metadata-Version: 2.1
Name: roq
Version: 0.0.2
Home-page: 
Author: Federico A. Galatolo
Author-email: federico.galatolo@unipi.it
Classifier: Programming Language :: Python :: 3.11
Classifier: License :: OSI Approved :: Apache Software License
Classifier: Operating System :: OS Independent
Classifier: Development Status :: 4 - Beta
License-File: LICENSE.txt
Requires-Dist: aiomqtt==2.0.1
Requires-Dist: paho-mqtt==1.6.1
